setup.py
dogebuild_fpc/__init__.py
dogebuild_fpc/fpc.py
dogebuild_fpc/loader.py
dogebuild_fpc.egg-info/PKG-INFO
dogebuild_fpc.egg-info/SOURCES.txt
dogebuild_fpc.egg-info/dependency_links.txt
dogebuild_fpc.egg-info/top_level.txt