Metadata-Version: 1.1
Name: dogebuild-fpc
Version: 0.1.0.dev1
Summary: Free Pascal Compiler plugin for dogebuild
Home-page: https://github.com/dogebuild/dogebuild-fpc
Author: Kirill Sulim
Author-email: kirillsulim@gmail.com
License: UNKNOWN
Keywords: dogebuild builder fpc pascal
Platform: UNKNOWN
Classifier: Development Status :: 2 - Pre-Alpha
Classifier: Environment :: Plugins
Classifier: Intended Audience :: Developers
Classifier: License :: OSI Approved :: MIT License
Classifier: Natural Language :: English
Classifier: Operating System :: OS Independent
Classifier: Programming Language :: Python :: 3.3
Classifier: Programming Language :: Python :: 3.4
Classifier: Topic :: Software Development
